src/__init__.py
src/cowork_history_server.py
cowork_history-4.0.3.dist-info/METADATA
cowork_history-4.0.3.dist-info/WHEEL
cowork_history-4.0.3.dist-info/entry_points.txt
cowork_history-4.0.3.dist-info/licenses/LICENSE
cowork_history-4.0.3.dist-info/RECORD
