Metadata-Version: 2.4
Name: cowork-history
Version: 4.0.3
Summary: Search and browse Claude conversation history with hybrid search (FTS + Spotlight + vector embeddings)
Project-URL: Homepage, https://github.com/egoughnour/cowork-history
Project-URL: Repository, https://github.com/egoughnour/cowork-history
Project-URL: Issues, https://github.com/egoughnour/cowork-history/issues
Author-email: Erik Goughnour <e.goughnour@gmail.com>
License: MIT
License-File: LICENSE
Keywords: claude,conversation,embeddings,history,mcp,model-context-protocol,ollama,search
Classifier: Development Status :: 4 - Beta
Classifier: Intended Audience :: Developers
Classifier: License :: OSI Approved :: MIT License
Classifier: Programming Language :: Python :: 3
Classifier: Programming Language :: Python :: 3.10
Classifier: Programming Language :: Python :: 3.11
Classifier: Programming Language :: Python :: 3.12
Classifier: Programming Language :: Python :: 3.13
Classifier: Topic :: Scientific/Engineering :: Artificial Intelligence
Requires-Python: >=3.10
Requires-Dist: fastmcp>=2.0.0
Requires-Dist: httpx>=0.27.0
Requires-Dist: pydantic>=2.0.0
Provides-Extra: dev
Requires-Dist: pytest-asyncio>=0.24.0; extra == 'dev'
Requires-Dist: pytest-cov>=4.0.0; extra == 'dev'
Requires-Dist: pytest>=8.0.0; extra == 'dev'
Requires-Dist: ruff>=0.1.0; extra == 'dev'
